CHANGES.md
LICENSE.txt
MANIFEST.in
README.md
setup.cfg
setup.py
navio/__init__.py
navio/meta_aws.py
navio/aws/__init__.py
navio/aws/_common.py
navio/aws/shared.py
navio/aws/services/__init__.py
navio/aws/services/_acm.py
navio/aws/services/_cloudformation.py
navio/aws/services/_cloudfront.py
navio/aws/services/_ec2.py
navio/aws/services/_iam.py
navio/aws/services/_lambda.py
navio/aws/services/_logs.py
navio/aws/services/_s3.py
navio/aws/services/_session.py
navio_aws.egg-info/PKG-INFO
navio_aws.egg-info/SOURCES.txt
navio_aws.egg-info/dependency_links.txt
navio_aws.egg-info/requires.txt
navio_aws.egg-info/top_level.txt